xhome/__init__.py
xhome/actuator.py
xhome/sensors.py
pop_xhome-1.0.0.dist-info/METADATA
pop_xhome-1.0.0.dist-info/WHEEL
pop_xhome-1.0.0.dist-info/top_level.txt
pop_xhome-1.0.0.dist-info/RECORD
